{
    "objects": [
        {
            "shots": [
                {
                    "entry": [
                        {
                            "anim": "#p8_fxanim_zm_mansion_prima_machine_idle_anim",
                            "entrytype": "anim"
                        }
                    ],
                    "name": "init"
                },
                {
                    "entry": [
                        {
                            "anim": "#hash_71b9a1e4979cee19",
                            "entrytype": "anim"
                        }
                    ],
                    "name": "open"
                },
                {
                    "entry": [
                        {
                            "anim": "#p8_fxanim_zm_mansion_prima_machine_start_anim",
                            "entrytype": "anim"
                        }
                    ],
                    "name": "start"
                },
                {
                    "entry": [
                        {
                            "anim": "#hash_7c380a8b2d15f17d",
                            "entrytype": "anim"
                        }
                    ],
                    "name": "finish"
                },
                {
                    "entry": [
                        {
                            "anim": "#hash_1c49cb51212581c5",
                            "entrytype": "anim"
                        }
                    ],
                    "name": "close"
                }
            ],
            "firstframe": 1,
            "model": "#p8_fxanim_zm_mansion_prima_machine_mod",
            "type": "prop",
            "name": "prop 1"
        },
        {
            "shots": [
                {
                    "entry": [
                        {
                            "anim": "#hash_39aa95f613dc2f43",
                            "entrytype": "anim"
                        }
                    ],
                    "name": "init"
                },
                {
                    "entry": [
                        {
                            "anim": "#hash_2dcfaee5af6612d0",
                            "entrytype": "anim"
                        }
                    ],
                    "name": "open"
                },
                {
                    "entry": [
                        {
                            "anim": "#hash_3963518cfe95563b",
                            "entrytype": "anim"
                        }
                    ],
                    "name": "start"
                },
                {
                    "entry": [
                        {
                            "anim": "#hash_7e75f2f6bd2fd76c",
                            "entrytype": "anim"
                        }
                    ],
                    "name": "finish"
                },
                {
                    "entry": [
                        {
                            "anim": "#hash_283cb033c96dcd10",
                            "entrytype": "anim"
                        }
                    ],
                    "name": "close"
                }
            ],
            "model": "#hash_2415e81880582ab9",
            "type": "prop",
            "name": "prop 2"
        }
    ],
    "scenetype": "fxanim",
    "configstringfiletype": "scriptbundle",
    "devstate": "placeholder",
    "type": "scene",
    "name": "p8_fxanim_zm_mansion_prima_machine_bundle",
    "dontsync": 1,
    "team": "any"
}