{
    "objects": [
        {
            "shots": [
                {
                    "entry": [
                        {
                            "anim": "#hash_2893b5c39f6312cd",
                            "entrytype": "anim"
                        }
                    ],
                    "name": "shot 1"
                }
            ],
            "model": "#hash_51e4d27b5d5d76cc",
            "type": "prop",
            "name": "prop 1"
        }
    ],
    "scenetype": "fxanim",
    "configstringfiletype": "scriptbundle",
    "looping": 1,
    "devstate": "placeholder",
    "type": "scene",
    "vmtype": "server",
    "name": "p8_fxanim_mp_offshore_crate_door_bundle",
    "dontsync": 1,
    "team": "any"
}