{
    "name": "#hash_6f04c3247c0717b1",
    "baseWeapon": "#zombie_builder",
    "streamkey": "#hash_6fde417d6197225",
    "soundb0": "#hash_321e0616ad37f67d",
    "firesound": "#hash_2058b0dbb3d49daa",
    "sound240": "#hash_631a067190b54300",
    "sound250": "#hash_242aa17124751841",
    "sound4e0": "#hash_7de02f3f0a5f070b",
    "tunables1": "#hash_7417797e5cfb06e8",
    "viewmodel": "#hash_20b1d428220",
    "tagFXSetFirstPerson": [],
    "tagFXSetThirdPerson": [],
    "underwaterExplosionSurfaceFX": []
}