{
    "name": "#straferun_rockets_mp",
    "baseWeapon": "#straferun_rockets",
    "unk70": "#straferun",
    "streamkey": "#hash_69baf19a7bc1072b",
    "unk90": "#hash_945e81fdb5864d8",
    "firesound": "#hash_6484de63f9e5b2f",
    "firesoundplayer": "#hash_6484de63f9e5b2f",
    "sound240": "#hash_631a067190b54300",
    "sound250": "#hash_242aa17124751841",
    "sound270": "#hash_4382ea72adea8a5c",
    "projexplosionsound": "#hash_66cd4495f61d5d89",
    "sound830": "#hash_36e25fd652fdfac2",
    "sound840": "#hash_7a5614b91f27d6ca",
    "tunables1": "#hash_1d942572228",
    "tagFXSetFirstPerson": [],
    "tagFXSetThirdPerson": [],
    "image_cb0": "#hash_f69fd7de2314b29a",
    "rumble_dc0": "#tank_fire_mp",
    "rumble_de8": "#grenade_rumble",
    "image_e90": "#hash_a7ba3c44ae920c9d",
    "projectilemodel": "#projectile_hellfire_missile",
    "fx_ed8": "#hash_1ae397a2f822f91f",
    "fx_f00": "#hash_209c0f28bb709b3c",
    "underwaterExplosionSurfaceFX": [],
    "var_2e4a8800": "#straferun_scoreevents"
}