{
    "name": "#ww_crossbow_charged_t8_zm",
    "baseWeapon": "#ww_crossbow_charged_t8",
    "displayname": "#zmweapon/ww_crossbow_t8",
    "unk70": "#ww_crossbow_t8",
    "streamkey": "#hash_7624ebe9ca15f15e",
    "unk90": "#hash_40d1ee977f5c102f",
    "firesound": "#hash_8719a4a195376f1",
    "firesoundplayer": "#hash_63a2f5734613eaaf",
    "sound220": "#hash_8719a4a195376f1",
    "sound230": "#hash_63a2f5734613eaaf",
    "sound240": "#hash_683733eab40de48b",
    "sound250": "#hash_3ee3cceae529ba86",
    "sound270": "#hash_24db08faf35699e1",
    "sound290": "#hash_3570e7ccea6bbaba",
    "projexplosionsound": "#poop1",
    "projexplosionsoundplayer": "#poop2",
    "sound800": "#hash_54f28bb508a46096",
    "sound810": "#hash_54f28bb508a46096",
    "tunables1": "#hash_1d986bbd694",
    "xcam_8e8": "#hash_fe16e91e9651857a",
    "xcam_8f0": "#hash_fe16e91e9651857a",
    "xcam_8f8": "#hash_b2556c49982dea72",
    "viewmodel": "#hash_1d955194c30",
    "sharedWeaponSounds_c08": "#crossbow",
    "tagFXSetFirstPerson": [],
    "tagFXSetThirdPerson": [],
    "image_cb0": "#reticle_crossbow",
    "image_d40": "#hash_c87f53ace056aca3",
    "rumble_dc0": "#crossbow_fire",
    "rumble_df8": "#hash_1b194e26c256036c",
    "image_e90": "#t7_icon_weapon_special_crossbow_kf",
    "projectilemodel": "#tag_origin",
    "fx_f00": "#hash_1cbb93dadf453751",
    "underwaterExplosionSurfaceFX": [],
    "fx_f88": "#hash_4542693a5b0810a0"
}