{
    "name": "#zombie_perk_bottle_death_dash",
    "baseWeapon": "#zombie_perk_bottle_death_dash",
    "streamkey": "#hash_41c19f1b64789d83",
    "soundb0": "#hash_321e0616ad37f67d",
    "firesound": "#hash_2058b0dbb3d49daa",
    "sound240": "#hash_631a067190b54300",
    "sound250": "#hash_242aa17124751841",
    "sound4e0": "#hash_7de02f3f0a5f070b",
    "tunables1": "#zombie_perk_bottle_death_dash_tunables",
    "viewmodel": "#hash_20b1dafcbf0",
    "tagFXSetFirstPerson": [],
    "tagFXSetThirdPerson": [],
    "underwaterExplosionSurfaceFX": []
}