{
    "itemlist": [
        {
            "minweight": 240,
            "itementry": "scriptbundle&global_list_guns_small_dlc1",
            "maxweight": 320,
            "available": -1
        },
        {
            "minweight": 85,
            "itementry": "scriptbundle&wind_turbine_list_health",
            "maxweight": 150,
            "available": -1
        },
        {
            "minweight": 150,
            "itementry": "scriptbundle&wind_turbine_list_equipment",
            "maxweight": 240,
            "available": -1
        },
        {
            "minweight": 33,
            "itementry": "scriptbundle&wind_turbine_list_gear",
            "maxweight": 58,
            "available": -1
        },
        {
            "minweight": 105,
            "itementry": "scriptbundle&wind_turbine_list_consumable",
            "maxweight": 180,
            "available": -1
        },
        {
            "minweight": 200,
            "itementry": "scriptbundle&wind_turbine_list_attachment",
            "maxweight": 300,
            "available": -1
        },
        {
            "minweight": 350,
            "itementry": "scriptbundle&wind_turbine_list_ammo",
            "maxweight": 400,
            "available": -1
        },
        {
            "minweight": 20,
            "itementry": "scriptbundle&storage_list",
            "maxweight": 30,
            "available": -1
        },
        {
            "minweight": 70,
            "itementry": "scriptbundle&wind_turbine_list_armor_shards",
            "maxweight": 70,
            "available": -1
        }
    ],
    "hash_3d685b35": 0,
    "configstringfiletype": "scriptbundle",
    "hash_7fb0967b": 420,
    "type": "itemspawnlist",
    "hash_345eba59": 9,
    "vehiclespawner": 0,
    "hash_9b009839": -1,
    "hash_dc7ffbef": 0,
    "name": "wind_turbine_list_items_small_dlc1",
    "supplystashweight": 100,
    "hash_dc91e192": 0
}