{
    "var_11cb9190": 1,
    "kshacktoolinnerradius": 1,
    "ksmainturretrecoilforce": -5,
    "ksshutdownonexit": 1,
    "var_5789ac76": 3,
    "var_f5871fe4": "requestfutzultturret",
    "var_6417048f": "#hash_453ecbd9693dd1d3",
    "ksburstfiremaxtime": 1.75,
    "ksburstfiredelaymintime": 1,
    "var_f1f399b4": 2,
    "var_c45a5808": 500,
    "var_33561c46": 2,
    "var_2aeadfa0": 2500,
    "ksdartwaittimeafterlastshot": 1.5,
    "var_1de74ef1": 40,
    "var_d3413870": "ultimate_turret",
    "var_5fbfc70d": "mpl_killstreak_auto_turret",
    "var_a22d6862": 1,
    "ksdartshotcount": 2,
    "var_2725e0d9": 500,
    "kshero_bowlauncher": 1,
    "var_7a88c1ea": 3,
    "var_799a81a7": "threatultturret",
    "var_3020f1b2": 32,
    "var_4be7d629": 7,
    "kshacktoolinnertime": 4000,
    "var_cbe1e532": 1,
    "var_2451b1f2": "enemyultturret",
    "var_502a0e23": "#hash_7b4c84d5307fea60",
    "kshero_gravityspikes": 1,
    "var_dabf2484": 200,
    "kstime": 180000,
    "var_3738674b": 0.5,
    "kshacktoolouterradius": 30,
    "var_218dc866": 6000,
    "var_98a3d82c": 1.8,
    "var_522ae074": 2,
    "var_1bc9830d": 1,
    "var_c14832cd": 1,
    "var_29dd9ea3": 0.5,
    "var_146c465e": 1.5,
    "var_665f5835": 0.5,
    "ksuseimmediately": 1,
    "var_c2f9c573": 6,
    "var_4704450c": 50,
    "var_e077ecb": 8500,
    "var_a11c1ea0": 2,
    "var_e856ec03": 1,
    "var_e572e323": 1,
    "type": "killstreak",
    "var_56f54dc0": 120,
    "var_1d2a2ca4": "#hash_2b0e1f9a3a18912b",
    "ksweapon": <error reading:ultimate_turret_wz>,
    "var_8c4d7906": "#hash_595d5ff7c52d0f12",
    "ksrobshowfriendly": 1,
    "var_ee9fdcf3": 200,
    "ksdamageradius": 750,
    "ksduration": 60000,
    "kshackscoreevent": "#hash_60910bb24a05d5bf",
    "var_bd7786a4": "destroyedultturret",
    "var_e5ca8662": 30,
    "var_b88f3e5a": 3,
    "ksvalidcarepackagelocationsound": "mpl_good_location_select",
    "ksinvalidlocationstring": "#hash_640c02977f1b2d13",
    "var_d6c2930c": 200,
    "ksrocketstokill": 1,
    "var_c9cb1de0": 500,
    "ksdartinitialspeed": 35,
    "ksplaceablehint": "#hash_56d772673f98a87b",
    "kshero_heatwave": 2,
    "var_676a4c7": 20,
    "vmtype": "both",
    "ksdartacceleration": 35,
    "var_b45be9e6": "#hash_4d30d1e5cbaf916",
    "var_2d890f85": 2,
    "ksshotgunenergytokill": 2,
    "var_dff95af": 300,
    "ksplaceableinvalidlocationhint": "#hash_1ec02a95496f3883",
    "var_540b2ab4": 100,
    "var_de725346": 2,
    "var_178f3ad6": 5,
    "var_e88fce4": 1,
    "var_ebd92bbc": "#hash_4768b9f8671445b3",
    "var_32e69cad": 9000,
    "var_ff3d4d40": 2,
    "var_cadb59a0": 100,
    "kshacktimeout": 20,
    "var_843b7bd3": 2,
    "var_8eca21ba": 2,
    "kshero_pineapplegun": 1,
    "var_7e0a4ef7": 10,
    "kshackprotection": 1,
    "name": "killstreak_ultimate_turret_wz",
    "ksweaponreloadtime": 1,
    "var_c28c2429": 30,
    "ksexplosioninnerdamage": 350,
    "var_ed4e0bcc": 300,
    "var_2f1567fb": 200,
    "ksrobfriendly": "rob_sonar_set_friendlyequip_mp",
    "ksmainturretrecoilforcecontrolled": -1,
    "var_a2629b1c": 100,
    "ksdartcamerawatchduration": 2,
    "kshacktoollostlineofsightlimitms": 3000,
    "var_1faee2a5": 0.25,
    "kslowhealth": 400,
    "kshacktoolnolineofsighttime": 6000,
    "ksdartcamerawatchdistance": 350,
    "var_b9443d6b": 2,
    "var_fa38350a": 2,
    "var_74711af9": "#hash_4768b9f8671445b3",
    "var_b32c8349": 5,
    "ksburstfiredelaymaxtime": 1.5,
    "kshackedhealth": 200,
    "kstotaldroptime": 4,
    "var_ea340924": 2,
    "var_ffbb43eb": 4000,
    "var_18d458d2": 10000,
    "var_366f43e9": 200,
    "var_efac0f7a": 4000,
    "var_f6853f02": 2500,
    "var_768e166a": 0.1,
    "var_9f7e68a3": 2000,
    "var_b45a7714": 0.25,
    "var_ee982290": 100,
    "var_d4f45bfd": 3000,
    "var_533663fb": 6000,
    "var_bd3080e0": 6000,
    "var_bb6c29b4": "#hash_416ab5cb13a9af8c",
    "var_7135d43f": 200,
    "var_e773a429": "requestultturret",
    "kshealth": 1500,
    "var_34225773": 2,
    "ksmeleedamagemultiplier": 1.7,
    "var_89c78a8e": 1,
    "ksinvalidlocationsound": "mpl_bad_location_select",
    "ksexplosionouterdamage": 25,
    "var_92f9f099": 3,
    "var_64e90954": 5,
    "var_cb7372f2": 10000,
    "ksrobenemy": "rob_sonar_set_enemyequip",
    "var_1f9faa0c": 12000,
    "var_3307f79d": 20,
    "ksexplosionouterradius": 200,
    "var_f936eadc": 300,
    "var_e7b30a9a": "ultturretdialogbundle",
    "var_667c638e": "#hash_780eae069af8c774",
    "ksdartstokill": 1,
    "kshero_firefly_swarm": 2,
    "ksshotgunmultiplier": 2,
    "var_dfbb227c": 0.5,
    "ksburstfiremintime": 1,
    "var_5fa88c50": 1000,
    "var_293cf5d4": "mpl_good_location_select",
    "var_bc2f6af9": "#hash_6541feae026c1180",
    "var_8e002961": 6,
    "ksremote_missile_missile": 1,
    "var_a562774d": 250,
    "var_368617ff": 10,
    "ksrobshowenemy": 1,
    "var_b4562c66": 5,
    "kshacktooloutertime": 40000,
    "kshero_annihilator": 1,
    "var_a9b0c301": 1,
    "ksstartcratekillheightfromground": 200,
    "ksvalidaitanklocationsound": "mpl_good_location_select",
    "var_d784077a": 1,
    "var_46783f3a": 0.65,
    "var_31cddd6": 2,
    "var_2a12121": 250,
    "var_dab62696": 50,
    "var_cea2a369": 0.4,
    "var_d7ff2d3e": 0.8,
    "var_f7478ae6": 200,
    "var_5a0d87e0": 20,
    "ksburstfireenabled": 1
}