{
    "var_6582a778": "#hash_664985f68e124204",
    "var_c5a434fd": "#hash_714af911db385ca1",
    "var_71e6f25": "#hash_5a9ece27ecd66e71",
    "var_d32aca42": "#hash_7c04974b5c53b0df",
    "exertsnipergasp": "#hash_4b252d0f7a91c220",
    "var_fc5812eb": "#hash_c029abd243b86cb",
    "exertradiationselfloop": "#hash_928e1b33842c653",
    "gravityslamweapondestroyed": "#hash_4f768185560f7c07",
    "var_e324183": "#hash_23f722a6249bb0b0",
    "var_ee880c80": "#hash_4c797e9039ac8c79",
    "var_f856201c": "#hash_4c797d9039ac8ac6",
    "var_5ddfeb2e": "#hash_4c797c9039ac8913",
    "var_6ec08ceb": "#hash_4c797b9039ac8760",
    "exertemergegasp": "#hash_16be5706e574caa6",
    "requestfutzsupplydrop": "#hash_1bab85a57d53b363",
    "var_68bb30c1": "#hash_23f29cd03fe5ce7b",
    "var_bbc9856": "#hash_5d6e791d8353a95e",
    "var_636a7895": "#hash_1199ee623532defc",
    "var_54475e1e": "#hash_71b6a7e5625396c",
    "var_63661ff": "#hash_6d5f17641844fe07",
    "var_8ba3822": "#hash_ed45f131a658867",
    "var_d3d0cdde": "#hash_44f6725c6b376d4",
    "var_c9b05b2e": "#hash_baf5f5dbe238b28",
    "var_dbeaffa3": "#hash_baf605dbe238cdb",
    "var_6d8c22e7": "#hash_baf615dbe238e8e",
    "var_7ec9c562": "#hash_baf625dbe239041",
    "laststanddown": "#hash_6aa33708d4ab1e1c",
    "var_69ee8f4a": "#hash_1efa0c4f4ed2528e",
    "requesthelicopter": "#hash_31698dc48bbd487c",
    "var_76c783b3": "#hash_386189fdceac17a1",
    "var_a10dd83f": "#hash_386188fdceac15ee",
    "var_da3aca98": "#hash_386187fdceac143b",
    "var_e879e716": "#hash_386186fdceac1288",
    "revive": "#hash_659a94594bf330ea",
    "var_3f4a1443": "#hash_6dd4be287f2262b1",
    "var_53f12400": "#hash_483b0b969ab452a1",
    "var_fc160cfc": "#hash_654f4d8aa832291b",
    "var_1da45018": "#hash_654f4c8aa8322768",
    "var_578243d3": "#hash_654f4f8aa8322c81",
    "var_94a2764": "#hash_654f4e8aa8322ace",
    "exertpainunderwater": "#hash_437282d6d9ccdbb1",
    "var_e6d1c1e3": "#hash_142ad4571b85d423",
    "requestcounteruav": "#hash_39e20ed842d253a1",
    "var_2f65caf3": "#hash_728c40a355303319",
    "threatinfantry": "#hash_1cbd8ea28348800a",
    "exertpaindrowning": "#hash_1e4d838ff0f3e816",
    "threatcounteruav": "#hash_305fb9790cecc962",
    "requestaitank": "#hash_e4f8143c6b1b9c0",
    "var_61f7feba": "#hash_60d9aabecf22995",
    "var_827669e9": "#hash_65821e693acb893f",
    "var_35a7e396": "#hash_1f0b3636df324a9b",
    "var_cb4d0ee2": "#hash_1f0b3536df3248e8",
    "var_12241c8f": "#hash_1f0b3836df324e01",
    "var_27d347ed": "#hash_1f0b3736df324c4e",
    "var_aa447d74": "#hash_54468ed15767b944",
    "var_922067c4": "scriptbundle",
    "var_54c097dc": "#hash_70d5ecba6895ecd8",
    "respawned": "#hash_2ac3307d00de9a45",
    "var_e4190328": "#hash_708799eed3cb49ad",
    "threatrpg": "#hash_6a7dd626e5df0c92",
    "var_94f7b414": "#hash_e583d6a76b92128",
    "supplypodweapondestroyed": "#hash_15e9edac703ae0d5",
    "killenemy": "#hash_f40effe7bc60c47",
    "var_b5677849": "#hash_7d7cabcbc10b002",
    "var_b50819f2": "#hash_47209ef24748510",
    "var_6f728fb2": "#hash_76a9c9cdc83f82bc",
    "var_efb67b32": "#hash_230167a8d9c1d066",
    "var_23824a56": "#hash_25e7e30f2c22d31c",
    "var_e765543e": "#hash_1e1a3b42725f72b4",
    "var_6505d47a": "#hash_7599542fc2a702b7",
    "var_a8809c1c": "#hash_1d8566d8123cdc3f",
    "var_e230637d": "#hash_124591c3f95d2230",
    "var_d2fd550a": "#hash_47ee4c62e518f090",
    "killsniper": "#hash_6875c432aac5c35c",
    "var_772dbd73": "#hash_7c6c58d95d508b73",
    "var_23b68936": "#hash_343a7f994e0ea03a",
    "var_96b4150c": "#hash_5c2070087f6db71d",
    "var_e4c5ee66": "#hash_5d86a9a37676c27b",
    "var_867d31d6": "#hash_5d86a8a37676c0c8",
    "var_7837954b": "#hash_5d86aba37676c5e1",
    "var_a9e2f8a1": "#hash_5d86aaa37676c42e",
    "threatuav": "#hash_75daef10c32bb16b",
    "exertbreathesprinting": "#hash_6b90c0825a5229a6",
    "requestuav": "#hash_143c7d286aed0fa2",
    "var_94daed2f": "#hash_52791471018ca110",
    "requestfutzrcbomb": "#hash_7a1fa2a1fd7c2be5",
    "var_812dd6ff": "#hash_2d7ee8a6d2548aae",
    "var_b5c7c032": "#hash_2d7ee9a6d2548c61",
    "var_aee73271": "#hash_2d7ee6a6d2548748",
    "var_5a5c895d": "#hash_2d7ee7a6d25488fb",
    "var_cf906c68": "#hash_2e06cb4088f57eba",
    "type": "mpdialog_player",
    "requestsupplydrop": "#hash_4507615e5eedd7",
    "battleshieldweapondestroyed": "#hash_2298e191d70a2394",
    "var_1ab815cb": "#hash_6de48fd2668e0a5d",
    "killgeneric": "#hash_433168763dd39498",
    "exertradiationselfend": "#hash_7ed5d9b331f09816",
    "sparrowweaponsuccess": "#hash_157bffe1a40a9e39",
    "requestfutzultturret": "#hash_a4d8aa690c17156",
    "var_b2a43c9c": "#hash_513f2991c8b76b8",
    "requestfutzplanemortar": "#hash_43761f63c078d4be",
    "var_1d06de0e": "#hash_1a08d7f72b87a9c",
    "destroyedultturret": "#hash_fb27c1e0e126db8",
    "requestfutzstraferun": "#hash_7ea3acbafac2fb54",
    "requeststraferun": "#hash_6742d3fcd71c2586",
    "requestplanemortar": "#hash_3c92a2fc1797dd78",
    "sparrowweapondestroyed": "#hash_1aadf91e23920d41",
    "armbladeweapondestroyed": "#hash_4b0b650629337f52",
    "var_f33cef89": "#hash_2e670954f282cf4e",
    "var_d0b5ae02": "#hash_4433ea5fac929daf",
    "exertaxethrow": "#hash_ed45f131a658867",
    "requestdart": "#hash_70b8c6aedb273433",
    "var_928f03c4": "#hash_3f6e37fae85d783e",
    "exertgasgag": "#hash_43aa5c9052615190",
    "callinfutzremotemissile": "#hash_5b4b7ba0e78bc1a3",
    "var_e79fdef1": "#hash_3212038e2aceb8d5",
    "exertpain": "#hash_76b631b77d128fe9",
    "var_5f891d60": "#hash_61fe0422972d1d15",
    "vmtype": "both",
    "exertradiationselfstart": "#hash_50303997390e0b03",
    "requestoverwatchhelicopter": "#hash_34d98f4aa75e8795",
    "var_1e441f88": "#hash_6ee9b31baf822937",
    "var_6793b226": "#hash_6ee9b21baf822784",
    "var_852eed58": "#hash_6ee9b51baf822c9d",
    "var_4c16fb2d": "#hash_6ee9b41baf822aea",
    "threatsniper": "#hash_2e238410222cb454",
    "var_faa66cb4": "#hash_413e60f47bc3151f",
    "exertsniperhold": "#hash_42c4738c4cbd1d0e",
    "var_568ad856": "#hash_291804e5ff27971",
    "requestfutzhelicopter": "#hash_30181f514940fa0a",
    "tempestweapondestroyed": "#hash_2d8f114aec4fe403",
    "var_93fb4152": "#hash_4a6b7b5d658ba24b",
    "var_6aeb7087": "#hash_40c90d94a1ef4bef",
    "var_5cb5d41c": "#hash_40c90c94a1ef4a3c",
    "var_c27e1fb7": "#hash_40c90f94a1ef4f55",
    "var_eabc7033": "#hash_40c90e94a1ef4da2",
    "var_f3745d99": "#hash_1d7e5bd81236aae0",
    "var_ce864f4c": "#hash_461d08616619cf40",
    "var_3e1a4fb8": "#hash_36ab4acc2f54ca3a",
    "var_4ef902be": "#hash_70c43891bbf9113",
    "var_991a9de3": "#hash_4c86f3ae26d83ed1",
    "var_5fdf57ca": "#hash_5c0fc6d15b9136a8",
    "var_44d86dec": "#hash_76c7b093e2a6ce5c",
    "threatultturret": "#hash_4550a780646381ed",
    "exertbreathesprintingend": "#hash_2c86df002469ab",
    "threatrcbomb": "#hash_af8c51ec3cd68aa",
    "destroyedoverwatchhelicopter": "#hash_63b048e585532b2f",
    "characterselect": "#hash_41c3a68b73cfc9f2",
    "var_987d028": "#hash_3dc9b5e50b7337cf",
    "var_1bfb0e39": "#hash_107becd7c1a8dcc9",
    "annihilatordestroyed": "#hash_5c3598c746f2a554",
    "destroyeduav": "#hash_45defbf94c8b93aa",
    "var_abd42456": "#hash_59dda8400113c94c",
    "var_8630d910": "#hash_59dda9400113caff",
    "var_abf12484": "#hash_59ddaa400113ccb2",
    "var_64be162b": "#hash_59ddab400113ce65",
    "name": "outrider",
    "var_207908de": "#hash_56d6820b87bc3c2c",
    "var_6a4b9d1b": "#hash_781ac9687b1d00a6",
    "var_29a98af1": "#hash_2d1968f848191a26",
    "var_b801796c": "#hash_12aab8a63758c0bb",
    "var_f072d2d2": "#hash_38fbadd0ff9f9876",
    "boostloss": "#hash_6b5aadff2e9c0999",
    "requestrcbomb": "#hash_716973f758acf629",
    "purifierweapondestroyed": "#hash_40e8be02ac67371c",
    "var_cfc7adfb": "#hash_12d74fd7648caf83",
    "var_5a7b473e": "#hash_525f8cee7da32605",
    "var_4164fcd1": "#hash_2fd21bf198a12223",
    "var_f261854": "#hash_2fd21af198a12070",
    "var_c5a78558": "#hash_2fd21df198a12589",
    "var_d3e621d5": "#hash_2fd21cf198a123d6",
    "exertgascough": "#hash_480b108a4956a75f",
    "var_426ce83a": "#hash_2a77966979cce5c1",
    "var_c4b4c50e": "#hash_21a8c7353f0ea21d",
    "var_93a2407e": "#hash_6c4d7e1242685b74",
    "var_6907b2ba": "#hash_3cf78a49ecf298de",
    "boostdraw": "#hash_553d54bd0144c6d0",
    "var_adaebe66": "#hash_183d950fc83d023f",
    "var_a9b96bba": "#hash_2265bce61bbbe14a",
    "var_cd4fb2e6": "#hash_2265bde61bbbe2fd",
    "var_bf6a171b": "#hash_2265bae61bbbdde4",
    "var_76bd05c2": "#hash_2265bbe61bbbdf97",
    "exertpainfalling": "#hash_76b631b77d128fe9",
    "destroyedcounteruav": "#hash_46bd0d8cd948b309",
    "var_140be686": "#hash_29ffdb1509b78227",
    "var_27b0d135": "#hash_431cd75ed1e37b0f",
    "heroweaponsuccessreaction": "#hash_2a42ec61d303b07a",
    "dogweapondestroyed": "#hash_382c2a1049979fd",
    "requestultturret": "#hash_43a1aedffece3f40",
    "var_41e91a42": "#hash_6da20b47f4272ba4",
    "var_53f25688": "#hash_48172f1edffe64f2",
    "exertdeath": "#hash_162ad1a7b12d03d9",
    "boostwin": "#hash_147de13c292631f0",
    "var_35e44265": "#hash_7fea11b173abc286",
    "destroyedrcbomb": "#hash_5b1cdb2f2208dd71",
    "var_75a78df2": "#hash_1266b2fef07877e",
    "exertdeathburned": "#hash_501c3066632fe35b",
    "var_443d5083": "#hash_3807e3e9caeaf832",
    "var_b4d5ca8f": "#hash_4b5717679bb5c357",
    "var_1dfcabbd": "#hash_68af08eac2635227",
    "threatoverwatchhelicopter": "#hash_767248a1b99afc64",
    "var_86fe45ae": "#hash_3a9835e5c2c622f8",
    "destroyedhelicopter": "#hash_7d75d9a9e96e32fa",
    "callinremotemissile": "#hash_484966135bc9ed17",
    "exertpaindamagetick": "#hash_7af6f74f3d5f9740",
    "exertgasgasp": "#hash_5ba4413bfb3b4354",
    "var_bbf7c71f": "#hash_4fd1df2407034fa2",
    "destroyedstraferun": "#hash_3915d11503e6ccf0",
    "var_c7859303": "#hash_3583600a181cee7e",
    "var_1d37ae8b": "#hash_155fcad676b5d21a",
    "var_606d0b06": "#hash_66baf6029701cb9e",
    "var_b8017b7c": "#hash_66997b01b45b77f5",
    "var_e4bd50dc": "#hash_7c7bdffe4de2e991",
    "var_e21e8b0a": "#hash_39bcad7d2c44b396",
    "var_15dfa8ec": "#hash_11dae95ffae81472",
    "threatstraferun": "#hash_725b803c9ea64325",
    "threathelicopter": "#hash_47e61fd8c2be89bb",
    "var_7c09c5ae": "#hash_40a66bebf7e7ff56",
    "exertdeathstabbed": "#hash_56d6820b87bc3c2c",
    "var_8e19817d": "#hash_7b11596f44fd8220",
    "hawkweapondestroyed": "#hash_24d8d2450f457db8",
    "var_4ce86d55": "#hash_70139943640015a6",
    "var_c62c0c00": "#hash_1019be70df8f7450",
    "exertsniperexhale": "#hash_18daca5089abb6ca",
    "var_2339275b": "#hash_796134670f1710de",
    "var_737bb295": "#hash_60e4aa62aaeec53a",
    "var_c6ca5931": "#hash_60e4ab62aaeec6ed",
    "var_8ff56b88": "#hash_60e4a862aaeec1d4",
    "var_6540161e": "#hash_60e4a962aaeec387",
    "sparrowweaponready": "#hash_3c40ac2346bc0a1d",
    "var_93ef961": "#hash_7f8c49cd00f6b069",
    "var_32dba6a": "#hash_73dc245e64bf686f",
    "exertemergebreath": "#hash_10532762fdee62d7",
    "stucksticky": "#hash_7cd43acaa46f335e",
    "reload": "#hash_51a4b3dfc52ee1d3",
    "exertdeathelectrocuted": "#hash_23f29cd03fe5ce7b",
    "var_f8b4bcc1": "#hash_189dee88c0c80a2b",
    "destroyeddart": "#hash_618e84261b0d491b",
    "requestfutzdart": "#hash_213597d8a2d928a7",
    "var_c41dc169": "#hash_591c6d0b039a4c84",
    "var_f1416960": "#hash_781538dc4cbcb1ed",
    "var_b51a051a": "#hash_58b42bf122819a4a",
    "var_ef5a5f33": "#hash_7fa773eaffb404a1",
    "var_fd98fbb0": "#hash_7fa772eaffb402ee",
    "var_11ca2412": "#hash_7fa771eaffb4013b",
    "var_fd847b6b": "#hash_7fa770eaffb3ff88",
    "var_4ea15dd3": "#hash_4f05c3aead36df60",
    "destroyedaitank": "#hash_a1ee8a0135218ae",
    "sparrowweaponuse": "#hash_4158652f65c8adf9",
    "var_327eb99c": "#hash_63b6c3014b278ef5",
    "var_fa5db24c": "#hash_64d17c8ea6a716a9",
    "promotionreaction": "#hash_1a738522ad0afdc3",
    "threataitank": "#hash_63cf6ebc4bc9c19f",
    "icepickweapondestroyed": "#hash_16673af17fb26b8d",
    "grapplegunweapondestroyed": "#hash_676b7520de0a5521",
    "var_1b7e4074": "#hash_69a5c0611f625445",
    "scytheweapondestroyed": "#hash_9c9e395cb1fdffb",
    "var_4fa3c4aa": "#hash_50c9d3478b192c0b",
    "var_decbe599": "#hash_48512cf4a5300e79",
    "var_f613c4d1": "#hash_29abdd3b7b1deed1",
    "exertfullyhealedbreath": "#hash_2ffaa82a0c7a5c3f",
    "requestfutzcounteruav": "#hash_4cb069151ea1792d",
    "exertdeathdrowned": "#hash_1e4d838ff0f3e816",
    "var_6f89cd5": "#hash_70d29e8a4b71009c",
    "requestfutzuav": "#hash_1a327d0dfcf605d8",
    "var_c3b67de0": "#hash_371a34935b17d23",
    "var_f671ae19": "#hash_2231063d40bfd1ab",
    "takingfire": "#hash_632575708dd52aef",
    "maldivescharacterselectoverride": "#hash_509a120b1b87e66",
    "requestfutzaitank": "#hash_4df993045bf2d0d6",
    "var_1ca33ad4": "#hash_4664e541f7d648d1",
    "var_9b5a2501": "#hash_165b1c3cc061d4d",
    "var_8a207103": "#hash_1ca985b0cbaa6e16",
    "var_f3b38bf6": "#hash_764f71e296cb57d3",
    "requestoverwatchfutzhelicopter": "#hash_703da8a465a80329",
    "radiationfieldweapondestroyed": "#hash_5c4d86d8b84d54e2",
    "var_e03ac407": "#hash_4feadc242b4cfd53",
    "var_a8199370": "#hash_4b14283979fd9fed",
    "warmachineweapondestroyed": "#hash_28cb60b215a9344f",
    "threatsupplydrop": "#hash_12c0bee70468c674",
    "var_4eb7770b": "#hash_7ac5a8607151547a"
}