{
    "destroyed": "#hash_40f6d4138dcaa08c",
    "ready": "#hash_50e28d94bdb94334",
    "configstringfiletype": "scriptbundle",
    "type": "mpdialog_scorestreak",
    "killmultiple": "#hash_5facc6a6527829c8",
    "vmtype": "both",
    "distancecheck": "#hash_7791480dad3b0195",
    "name": "cdp_taacom_kls_dart",
    "hacked": "#hash_55c3abdca57d9612",
    "kill1": "#hash_470eff792e8cd495",
    "kill3": "#hash_470efd792e8cd12f",
    "kill2": "#hash_470efc792e8ccf7c",
    "killnone": "#hash_2dfda626ff070667"
}