{
    "hasmigration": 1,
    "lobbymode": 0,
    "id": 2300,
    "settingscount": 1,
    "backtarget": "director_online_zm_pregame",
    "maxlocalclientsnetwork": 1,
    "mainmode": 2,
    "hash_d16ccae8": 0,
    "isprivate": 1,
    "showteams": 0,
    "lobbytype": 1,
    "menumusic": "lobby_zm",
    "room": "zm_online",
    "hash_7f60c82f": 4,
    "kicker": "localized17#hash_69818a6a90daf973",
    "isadvertised": 1,
    "maxclients": 4,
    "name": "director_online_zm_public",
    "networkmode": 2,
    "errtarget": "director_online_zm_pregame",
    "egamemodes": 0,
    "hash_ec76767d": 4,
    "title": "localized17#menu/zombie",
    "hash_f68d7d0": 2,
    "isgame": 1,
    "maxlocalclients": 2,
    "hash_38c7a0d1": "showdirectorpublic"
}